{
  "arxiv_id": "2506.14567v2",
  "title": "Multi-Tenant Access Control with Homomorphic Encryption",
  "authors": [
    {
      "name": "Elena Rodriguez",
      "affiliation": "Stanford Computer Science"
    },
    {
      "name": "James Wilson",
      "affiliation": "Stanford AI Lab"
    }
  ],
  "published": "2025-06-15T16:34:22Z",
  "pages": 19,
  "relevance_score": 85,
  "query_id": "3.8",
  "downloaded_date": "2026-01-10T18:28:21.383709",
  "key_topics": [
    "access_control",
    "policy",
    "authorization"
  ],
  "cluster_type": "Cluster 3",
  "abstract": "Presents cryptographic approach to multi-tenant isolation using homomorphic encryption for policy evaluation in shared infrastructure.",
  "doi": "10.48550/arXiv.2506.14567",
  "source": "ArXiv"
}