{
  "arxiv_id": "2512.06048",
  "title": "The Road of Adaptive AI for Precision in Cybersecurity",
  "authors": [
    "Sahil Garg"
  ],
  "published": "2025-12-05T10:16:45Z",
  "url": "http://arxiv.org/abs/2512.06048",
  "pdf_url": "http://arxiv.org/pdf/2512.06048.pdf",
  "relevance_score": 86,
  "summary": "Cybersecurity's evolving complexity presents unique challenges and opportunities for AI research and practice. This paper shares key lessons and insights from designing, building, and operating production-grade GenAI pipelines in cybersecurity, with a focus on the continual adaptation required to keep pace with ever-shifting knowledge bases, tooling, and threats. Our goal is to provide an actionable perspective for AI practitioners and industry stakeholders navigating the frontier of GenAI for c"
}