{
  "arxiv_id": "2407.02268v2",
  "title": "Footprints of Data in a Classifier: Understanding the Privacy Risks and Solution Strategies",
  "authors": [
    "Payel Sadhukhan",
    "Tanujit Chakraborty"
  ],
  "published": "2024-07-02T13:56:37Z",
  "summary": "The widespread deployment of Artificial Intelligence (AI) across government and private industries brings both advancements and heightened privacy and security concerns. Article 17 of the General Data Protection Regulation (GDPR) mandates the Right to Erasure, requiring data to be permanently removed from a system to prevent potential compromise. While existing research primarily focuses on erasing sensitive data attributes, several passive data compromise mechanisms remain underexplored and una",
  "cluster": "cluster_7",
  "classification": "GREEN",
  "relevance_score": 80,
  "screened_at": "2026-01-11T11:46:04.202376"
}