{
  "arxiv_id": "2512.24683v1",
  "title": "Waste-to-Energy-Coupled AI Data Centers: Cooling Efficiency and Grid Resilience",
  "authors": [
    "Qi He",
    "Chunyu Qu"
  ],
  "affiliation": "",
  "published_date": "2025-12-31",
  "url": "https://arxiv.org/abs/2512.24683v1",
  "relevance_score": 86,
  "key_topics": [],
  "summary": "AI data-center expansion is increasingly constrained by the coupled availability of deliverable electricity and heat-rejection (cooling) capacity. We propose and evaluate an integrated Waste-to-Energy"
}