{
  "arxiv_id": "2512.24350v1",
  "title": "Self-Gravitating Scalar Field Configurations, Ultra Light Dark Matter and Galactic Scale Observations",
  "authors": [
    "Bihag Dave"
  ],
  "affiliation": "",
  "published_date": "2025-12-30",
  "url": "https://arxiv.org/abs/2512.24350v1",
  "relevance_score": 94,
  "key_topics": [],
  "summary": "In this thesis, we investigate the possibility that dark matter consists of ultra light spin-zero particles with mass $m \\sim 10^{-22}\\ \\text{eV}$. We focus on the role of self-interactions, assuming "
}