{
  "arxiv_id": "2509.16030v1",
  "title": "A High-performance Real-time Container File Monitoring Approach Based on Virtual Machine Introspection",
  "authors": [
    "Kai Tan",
    "Dongyang Zhan",
    "Lin Ye",
    "Hongli Zhang",
    "Binxing Fang"
  ],
  "published_date": "2025-09",
  "url": "https://arxiv.org/abs/2509.16030v1",
  "relevance_score": 82.4,
  "estimated_pages": 10,
  "summary": "As cloud computing continues to advance and become an integral part of modern IT infrastructure, container security has emerged as a critical factor in ensuring the smooth operation of cloud-native applications. An attacker can attack the service in the container or even perform the container escape attack by tampering with the files. Monitoring container files is important for APT detection and c"
}