{
  "arxiv_id": "2011.07586",
  "title": "Uncertainty as a Form of Transparency: Measuring, Communicating, and Using Uncertainty",
  "authors": [
    "Umang Bhatt",
    "Javier Antor\u00e1n",
    "Yunfeng Zhang",
    "Q. Vera Liao",
    "Prasanna Sattigeri"
  ],
  "published": "2020-11-15",
  "relevance_score": 53,
  "url": "https://arxiv.org/abs/2011.07586",
  "summary": "Algorithmic transparency entails exposing system properties to various stakeholders for purposes that include understanding, improving, and contesting predictions. Until now, most research into algori"
}