{
  "arxiv_id": "2403.14641",
  "title": "Testing autonomous vehicles and AI: perspectives and challenges from cybersecurity, transparency, robustness and fairness",
  "authors": [
    "David Fern\u00e1ndez Llorca",
    "Ronan Hamon",
    "Henrik Junklewitz",
    "Kathrin Grosse",
    "Lars Kunze"
  ],
  "published": "2024-02-21",
  "relevance_score": 65,
  "url": "https://arxiv.org/abs/2403.14641",
  "summary": "This study explores the complexities of integrating Artificial Intelligence (AI) into Autonomous Vehicles (AVs), examining the challenges introduced by AI components and the impact on testing procedur"
}