{
  "arxiv_id": "2512.21377v1",
  "title": "A Systematic Review of Technical Defenses Against Software-Based Cheating in Online Multiplayer Games",
  "authors": [
    "Adwa Alangari",
    "Ohoud Alharbi"
  ],
  "published_date": "2025-12",
  "url": "https://arxiv.org/abs/2512.21377v1",
  "relevance_score": 91.2,
  "estimated_pages": 8,
  "summary": "This systematic literature review surveys technical defenses against software-based cheating in online multiplayer games. Categorizing existing approach-es into server-side detection, client-side anti-tamper, kernel-level anti-cheat drivers, and hardware-assisted TEEs. Each category is evaluated in terms of detection effectiveness, perfor-mance overhead, privacy im-pact, and scalability. The analy"
}